rotop/__init__.py
rotop/__main__.py
rotop/_version.py
rotop/data_container.py
rotop/gui_main.py
rotop/rotop.py
rotop/top_runner.py
rotop/utility.py
rotop/version_dummy.py
rotop-1.0.5.dist-info/LICENSE
rotop-1.0.5.dist-info/METADATA
rotop-1.0.5.dist-info/WHEEL
rotop-1.0.5.dist-info/entry_points.txt
rotop-1.0.5.dist-info/top_level.txt
rotop-1.0.5.dist-info/RECORD
